{
  "baseCurrency": "USD",
  "fetchedAtUtc": "2026-04-06T03:11:44.0479507Z",
  "source": "fawaz.exchange-api",
  "sourceKind": 2,
  "ratesFromBase": {
    "EUR": 0.86811129,
    "BTC": 0.000014891951,
    "USD": 1,
    "ETH": 0.00048561878,
    "MOP": 8.07253499,
    "NZD": 1.75894323,
    "SGD": 1.2870165,
    "JPY": 159.65108595,
    "CNY": 6.88489482,
    "AUD": 1.45124203,
    "TWD": 32.00067545,
    "CHF": 0.79995376,
    "GBP": 0.75756635,
    "CAD": 1.39453708,
    "HKD": 7.83741261
  }
}
